invenio_accounts/__init__.py
invenio_accounts/admin.py
invenio_accounts/api.py
invenio_accounts/cli.py
invenio_accounts/config.py
invenio_accounts/datastore.py
invenio_accounts/domains.py
invenio_accounts/errors.py
invenio_accounts/ext.py
invenio_accounts/forms.py
invenio_accounts/hash.py
invenio_accounts/models.py
invenio_accounts/proxies.py
invenio_accounts/sessions.py
invenio_accounts/signals.py
invenio_accounts/tasks.py
invenio_accounts/testutils.py
invenio_accounts/utils.py
invenio_accounts/alembic/037afe10e9ff_add_user_moderation_fields.py
invenio_accounts/alembic/62efc52773d4_create_useridentity_table.py
invenio_accounts/alembic/6ec5ce377ca3_create_domains.py
invenio_accounts/alembic/843bc79c426f_create_accounts_branch.py
invenio_accounts/alembic/9848d0149abd_create_accounts_tables.py
invenio_accounts/alembic/999dcbd19ace_users_versioning.py
invenio_accounts/alembic/dfbdf43a3e96_separate_login_info.py
invenio_accounts/alembic/e12419831262_add_new_columns_on_sessionactivity.py
invenio_accounts/alembic/eb9743315a9d_add_userprofile.py
invenio_accounts/alembic/f2522cdd5fcd_change_accountsrole_primary_key_to_string.py
invenio_accounts/context_processors/__init__.py
invenio_accounts/context_processors/jwt.py
invenio_accounts/profiles/__init__.py
invenio_accounts/profiles/dicts.py
invenio_accounts/profiles/schemas.py
invenio_accounts/templates/invenio_accounts/_macros.html
invenio_accounts/templates/invenio_accounts/base.html
invenio_accounts/templates/invenio_accounts/base_cover.html
invenio_accounts/templates/invenio_accounts/change_password.html
invenio_accounts/templates/invenio_accounts/forgot_password.html
invenio_accounts/templates/invenio_accounts/jwt.html
invenio_accounts/templates/invenio_accounts/login_user.html
invenio_accounts/templates/invenio_accounts/register_user.html
invenio_accounts/templates/invenio_accounts/reset_password.html
invenio_accounts/templates/invenio_accounts/send_confirmation.html
invenio_accounts-6.2.2.dist-info/licenses/AUTHORS.rst
invenio_accounts-6.2.2.dist-info/licenses/LICENSE
invenio_accounts-6.2.2.dist-info/METADATA
invenio_accounts-6.2.2.dist-info/WHEEL
invenio_accounts-6.2.2.dist-info/entry_points.txt
invenio_accounts-6.2.2.dist-info/top_level.txt
invenio_accounts-6.2.2.dist-info/RECORD
