Metadata-Version: 2.4
Name: invenio-accounts
Version: 6.2.2
Summary: Invenio user management and authentication.
Home-page: https://github.com/inveniosoftware/invenio-accounts
Author: CERN
Author-email: info@inveniosoftware.org
License: MIT
Keywords: invenio accounts user role login
Platform: any
Classifier: Development Status :: 5 - Production/Stable
Requires-Python: >=3.7
License-File: LICENSE
License-File: AUTHORS.rst
Requires-Dist: cryptography>=3.0.0
Requires-Dist: Flask-KVSession-Invenio>=0.6.3
Requires-Dist: Flask-Security-Invenio>=3.3.0
Requires-Dist: invenio-celery<3.0.0,>=2.0.0
Requires-Dist: invenio-i18n<4.0.0,>=3.0.0
Requires-Dist: invenio-mail<3.0.0,>=1.0.2
Requires-Dist: invenio-rest<3.0.0,>=2.0.0
Requires-Dist: invenio-theme<5.0.0,>=4.0.0
Requires-Dist: maxminddb-geolite2>=2017.404
Requires-Dist: pyjwt>=1.5.0
Requires-Dist: simplekv>=0.11.2
Requires-Dist: ua-parser>=0.7.3
Provides-Extra: admin
Requires-Dist: invenio-admin<2.0.0,>=1.2.1; extra == "admin"
Provides-Extra: postgresql
Requires-Dist: invenio-db[postgresql]<3.0.0,>=2.0.0; extra == "postgresql"
Provides-Extra: mysql
Requires-Dist: invenio-db[mysql]<3.0.0,>=2.0.0; extra == "mysql"
Provides-Extra: sqlite
Requires-Dist: invenio-db<3.0.0,>=2.0.0; extra == "sqlite"
Provides-Extra: tests
Requires-Dist: mock>=1.3.0; extra == "tests"
Requires-Dist: invenio-app<3.0.0,>=2.0.0; extra == "tests"
Requires-Dist: pytest-black-ng>=0.4.0; extra == "tests"
Requires-Dist: pytest-invenio<4.0.0,>=3.0.0; extra == "tests"
Requires-Dist: sphinx>=5; extra == "tests"
Dynamic: license-file
